xrit/__init__.py
xrit/packetmanager.py
xrit/packetmanager/__init__.py
xrit-1.0.5.dist-info/DESCRIPTION.rst
xrit-1.0.5.dist-info/METADATA
xrit-1.0.5.dist-info/RECORD
xrit-1.0.5.dist-info/WHEEL
xrit-1.0.5.dist-info/entry_points.txt
xrit-1.0.5.dist-info/metadata.json
xrit-1.0.5.dist-info/top_level.txt
