Metadata-Version: 2.0
Name: xrit
Version: 1.0.5
Summary: xRIT Parser
Home-page: https://github.com/opensatelliteproject/xritparser
Author: OpenSatelliteProject
Author-email: lucas@teske.net.br
License: MIT
Download-URL: https://github.com/opensatelliteproject/xritparser/tarball/1.0.5
Keywords: development sathelper opensatelliteproject satellite goes lrit hrit xrit noaa ccsds
Platform: UNKNOWN
Classifier: Development Status :: 4 - Beta
Classifier: Intended Audience :: Developers
Classifier: Topic :: Software Development :: Build Tools
Classifier: License :: OSI Approved :: MIT License
Classifier: Programming Language :: Python :: 2.6
Classifier: Programming Language :: Python :: 2.7
Classifier: Programming Language :: Python :: 3
Classifier: Programming Language :: Python :: 3.3
Classifier: Programming Language :: Python :: 3.4
Classifier: Programming Language :: Python :: 3.5
Requires-Dist: Pillow
Provides-Extra: dev
Requires-Dist: check-manifest; extra == 'dev'
Provides-Extra: test
Requires-Dist: coverage; extra == 'test'
